.coveragerc
.gitignore
CHANGES.rst
LICENSE.txt
README.rst
development.ini
i18n.sh
pytest.ini
setup.cfg
setup.py
.github/workflows/mysql.yml
.github/workflows/postgres.yml
.github/workflows/sqlite.yml
kotti_image/__init__.py
kotti_image/interfaces.py
kotti_image/resources.py
kotti_image.egg-info/PKG-INFO
kotti_image.egg-info/SOURCES.txt
kotti_image.egg-info/dependency_links.txt
kotti_image.egg-info/not-zip-safe
kotti_image.egg-info/requires.txt
kotti_image.egg-info/top_level.txt
kotti_image/alembic/script.py.mako
kotti_image/alembic/versions/.gitkeep
kotti_image/locale/kotti_image.pot
kotti_image/locale/de/LC_MESSAGES/kotti_image.mo
kotti_image/locale/de/LC_MESSAGES/kotti_image.po
kotti_image/templates/image.pt
kotti_image/tests/conftest.py
kotti_image/tests/logo.png
kotti_image/tests/sendeschluss.jpg
kotti_image/tests/test_functional.py
kotti_image/tests/test_scaling.py
kotti_image/views/__init__.py
kotti_image/views/edit.py